daiego43_rasptank/__init__.py
daiego43_rasptank/rasptank.py
daiego43_rasptank/camera/Camera.py
daiego43_rasptank/camera/__init__.py
daiego43_rasptank/distancesensor/Ultrasonic.py
daiego43_rasptank/distancesensor/__init__.py
daiego43_rasptank/distancesensor/gpiozerodistance.py
daiego43_rasptank/linesensor/LineSensor.py
daiego43_rasptank/linesensor/__init__.py
daiego43_rasptank/motor/Motor.py
daiego43_rasptank/motor/__init__.py
daiego43_rasptank/servo/Servo.py
daiego43_rasptank/servo/__init__.py
daiego43_rasptank-0.0.9.dist-info/METADATA
daiego43_rasptank-0.0.9.dist-info/WHEEL
daiego43_rasptank-0.0.9.dist-info/top_level.txt
daiego43_rasptank-0.0.9.dist-info/RECORD
